pyhelpme/__init__.py
pyhelpme/ahps.py
pyhelpme/coast.py
pyhelpme/download.py
pyhelpme/geog.py
pyhelpme/metrics.py
pyhelpme/norms.py
pyhelpme/params.py
pyhelpme/plot_geog.py
pyhelpme/polar.py
pyhelpme/wrf.py
pyhelpme/xrvar.py
pyhelpme-1.3.1.dist-info/LICENSE.txt
pyhelpme-1.3.1.dist-info/METADATA
pyhelpme-1.3.1.dist-info/WHEEL
pyhelpme-1.3.1.dist-info/top_level.txt
pyhelpme-1.3.1.dist-info/RECORD
