Metadata-Version: 2.2
Name: pyhelpme
Version: 1.3.1
Summary: Python Utilities
Home-page: https://github.com/ankurk017/pyhelpme
Author: Ankur Kumar
Author-email: ankurk017@gmail.com
License: MIT
License-File: LICENSE.txt
Requires-Dist: cartopy
Requires-Dist: matplotlib
Requires-Dist: numpy
Requires-Dist: xarray
Dynamic: author
Dynamic: author-email
Dynamic: description
Dynamic: home-page
Dynamic: license
Dynamic: requires-dist
Dynamic: summary
